pmlib/__init__.py
pmlib/cli.py
pmlib/ppm.py
pmlib/utils/__init__.py
pmlib/utils/args.py
pmlib/utils/colors.py
pmlib/utils/configurator.py
pmlib/utils/log.py
pmlib/utils/settings.py
pmppm-1.1.data/data/__init__.py
pmppm-1.1.data/data/args.py
pmppm-1.1.data/data/cli.py
pmppm-1.1.data/data/colors.py
pmppm-1.1.data/data/configurator.py
pmppm-1.1.data/data/log.py
pmppm-1.1.data/data/ppm.py
pmppm-1.1.data/data/settings.py
pmppm-1.1.dist-info/METADATA
pmppm-1.1.dist-info/WHEEL
pmppm-1.1.dist-info/entry_points.txt
pmppm-1.1.dist-info/top_level.txt
pmppm-1.1.dist-info/RECORD
