Metadata-Version: 2.1
Name: pmppm
Version: 1.1
Summary: Python Project Manager
Home-page: https://github.com/unitythecoder/ppm
Author: unitythecoder
Author-email: 
Requires-Dist: inquirer
